calculadora/__init__.py
calculadora/divide.py
calculadora/multiplica.py
calculadora/soma.py
calculadora/subtrai.py
calculadora_package_jcnok-0.0.1.dist-info/METADATA
calculadora_package_jcnok-0.0.1.dist-info/WHEEL
calculadora_package_jcnok-0.0.1.dist-info/top_level.txt
calculadora_package_jcnok-0.0.1.dist-info/RECORD
