Metadata-Version: 2.1
Name: calculadora-package-jcnok
Version: 0.0.1
Summary: Meu primeiro pacote
Home-page: https://github.com/Jcnok/myfirst_package.git
Author: Julio Okuda
Author-email: julio.okuda@gmail.com
License: UNKNOWN
Platform: UNKNOWN
Requires-Python: >=3.8.10
